Workbook

Sheet 決算入力
K1: コード | L1: 銘柄名 | N1: 決算年 | O1: 決算月 | P1: 更新日
K2: 2206 | L2: 江崎グリコ株式会社 | N2: 2025 | O2: 12 | P2: =NOW() -> 46080.831
A3: ■時系列決算データ比較
C4: =LEFT(F4,4)-1&"年" -> 2021年 | D4: =G4 -> 12 月期 | E4: 構成比 | F4: =LEFT(I4,4)-1&"年" -> 2022年 | G4: =J4 -> 12 月期 | H4: 構成比 | I4: =LEFT(L4,4)-1&"年" -> 2023年 | J4: =M4 -> 12 月期 | K4: 構成比 | L4: =LEFT(O4,4)-1&"年" -> 2024年 | M4: =P4 -> 12 月期 | N4: 構成比 | O4: =N2 &" 年" -> 2025 年 | P4: =O2 &" 月期" -> 12 月期 | Q4: 構成比
B5: 売上高 | D5: 338571 | E5: 百万 | G5: 303921 | H5: =E5 -> 百万 | J5: 332590 | K5: =E5 -> 百万 | M5: 331129 | N5: =E5 -> 百万 | P5: =IF(P30,P30,IF(M30,M30,IF(J30,J30,IF(G30,G30,IF(D30,D30,0))))) -> 0 | Q5: =H5 -> 百万
B6: 売上原価 | D6: 180537 | E6: =IF(D$5,D6/D$5,"-") -> 0.53323232 | G6: 193172 | H6: =IF(G$5,G6/G$5,"-") -> 0.63559938 | J6: 208740 | K6: =IF(J$5,J6/J$5,"-") -> 0.62761959 | M6: 203461 | N6: =IF(M$5,M6/M$5,"-") -> 0.61444633 | Q6: =IF(P$5,P6/P$5,"-") -> -
B7: 売上総利益 | D7: 158033 | E7: =IF(D$5,D7/D$5,"-") -> 0.46676473 | G7: 110749 | H7: =IF(G$5,G7/G$5,"-") -> 0.36440062 | J7: 123850 | K7: =IF(J$5,J7/J$5,"-") -> 0.37238041 | M7: 127668 | N7: =IF(M$5,M7/M$5,"-") -> 0.38555367 | Q7: =IF(P$5,P7/P$5,"-") -> -
B8: 販管費 | D8: 138726 | E8: =IF(D$5,D8/D$5,"-") -> 0.40973976 | G8: 97903 | H8: =IF(G$5,G8/G$5,"-") -> 0.32213305 | J8: 105228 | K8: =IF(J$5,J8/J$5,"-") -> 0.31638955 | M8: 116602 | N8: =IF(M$5,M8/M$5,"-") -> 0.35213467 | Q8: =IF(P$5,P8/P$5,"-") -> -
B9: 営業利益 | D9: 19307 | E9: =IF(D$5,D9/D$5,"-") -> 0.057024967 | G9: 12845 | H9: =IF(G$5,G9/G$5,"-") -> 0.042264273 | J9: 18622 | K9: =IF(J$5,J9/J$5,"-") -> 0.05599086 | M9: 11065 | N9: =IF(M$5,M9/M$5,"-") -> 0.03341598 | Q9: =IF(P$5,P9/P$5,"-") -> -
B10: 経常利益 | D10: 21708 | E10: =IF(D$5,D10/D$5,"-") -> 0.064116537 | G10: 13646 | H10: =IF(G$5,G10/G$5,"-") -> 0.044899826 | J10: 21285 | K10: =IF(J$5,J10/J$5,"-") -> 0.063997715 | M10: 13348 | N10: =IF(M$5,M10/M$5,"-") -> 0.040310574 | P10: =IF(P31,P31,IF(M31,M31,IF(J31,J31,IF(G31,G31,IF(D31,D31,0))))) -> 0 | Q10: =IF(P$5,P10/P$5,"-") -> -
B11: 純利益 | D11: 13567 | E11: =IF(D$5,D11/D$5,"-") -> 0.040071359 | G11: 8156 | H11: =IF(G$5,G11/G$5,"-") -> 0.026835921 | J11: 14219 | K11: =IF(J$5,J11/J$5,"-") -> 0.042752338 | M11: 8157 | N11: =IF(M$5,M11/M$5,"-") -> 0.024633904 | P11: =IF(P32,P32,IF(M32,M32,IF(J32,J32,IF(G32,G32,IF(D32,D32,0))))) -> 0 | Q11: =IF(P$5,P11/P$5,"-") -> -
B13: 発行株数 | D13: 68468 | E13: 千株 | G13: 68468 | H13: =E13 -> 千株 | J13: 68468 | K13: =H13 -> 千株 | M13: 68468 | N13: =K13 -> 千株 | P13: =IF(P40,P40,IF(M40,M40,IF(J40,J40,IF(G40,G40,IF(D40,D40,0))))) -> 68468 | Q13: =N13 -> 千株
B14: EPS／PER | D14: =IF(D13,D10*1000*0.7/D13,0) -> 221.93726 | E14: =IF(D14,D26/D14,0) -> 0 | G14: =IF(G13,G10*1000*0.7/G13,0) -> 139.51335 | H14: =IF(G14,G26/G14,0) -> 0 | J14: =IF(J13,J10*1000*0.7/J13,0) -> 217.61261 | K14: =IF(J14,J26/J14,0) -> 0 | M14: =IF(M13,M10*1000*0.7/M13,0) -> 136.46667 | N14: =IF(M14,M26/M14,0) -> 0 | P14: =IF(P13,P10*1000*0.7/P13,0) -> 0 | Q14: =IF(P14,P26/P14,0) -> 0
C16: 資産 | D16: 資本 | E16: 負債 | F16: 資産 | G16: 資本 | H16: 負債 | I16: 資産 | J16: 資本 | K16: 負債 | L16: 資産 | M16: 資本 | N16: 負債 | O16: 資産 | P16: 資本 | Q16: 負債
B17: バランスシート | C17: 356745 | D17: 241177 | E17: =C17-D17 -> 115568 | F17: 369056 | G17: 244760 | H17: =F17-G17 -> 124296 | I17: 395743 | J17: 263116 | K17: =I17-J17 -> 132627 | L17: 377771 | M17: 272598 | N17: =L17-M17 -> 105173 | O17: =IF(O44,O44,IF(L44,L44,IF(I44,I44,IF(F44,F44,IF(C44,C44,0))))) -> #VALUE! | P17: =IF(P44,P44,IF(M44,M44,IF(J44,J44,IF(G44,G44,IF(D44,D44,0))))) -> #VALUE! | Q17: =O17-P17 -> #VALUE!
B18: BPS／PBR | C18: =IF(C17,D17/C17,0) -> 0.67604872 | D18: =IF(D13,D17/D13*1000,0) -> 3522.4777 | E18: =IF(D18,D26/D18,0) -> 0 | F18: =IF(F17,G17/F17,0) -> 0.66320558 | G18: =IF(G13,G17/G13*1000,0) -> 3574.8087 | H18: =IF(G18,G26/G18,0) -> 0 | I18: =IF(I17,J17/I17,0) -> 0.66486583 | J18: =IF(J13,J17/J13*1000,0) -> 3842.9047 | K18: =IF(J18,J26/J18,0) -> 0 | L18: =IF(L17,M17/L17,0) -> 0.72159589 | M18: =IF(M13,M17/M13*1000,0) -> 3981.3928 | N18: =IF(M18,M26/M18,0) -> 0 | O18: =IF(O17,P17/O17,0) -> #VALUE! | P18: =IF(P13,P17/P13*1000,0) -> #VALUE! | Q18: =IF(P18,P26/P18,0) -> #VALUE!
B19: 財務レバレッジ補正 | C19: =IF(D17*C17>0,IF((1/(D17/C17+0.33))<1,1,IF((1/(D17/C17+0.33))>1.5,1.5,1/(D17/C17+0.33))),0) -> 1 | F19: =IF(G17*F17>0,IF((1/(G17/F17+0.33))<1,1,IF((1/(G17/F17+0.33))>1.5,1.5,1/(G17/F17+0.33))),0) -> 1.0068409 | I19: =IF(J17*I17>0,IF((1/(J17/I17+0.33))<1,1,IF((1/(J17/I17+0.33))>1.5,1.5,1/(J17/I17+0.33))),0) -> 1.0051607 | L19: =IF(M17*L17>0,IF((1/(M17/L17+0.33))<1,1,IF((1/(M17/L17+0.33))>1.5,1.5,1/(M17/L17+0.33))),0) -> 1 | O19: =IF(P17*O17>0,IF((1/(P17/O17+0.33))<1,1,IF((1/(P17/O17+0.33))>1.5,1.5,1/(P17/O17+0.33))),0) -> #VALUE!
C20: 営業 | D20: 投資 | E20: 財務 | F20: 営業 | G20: 投資 | H20: 財務 | I20: 営業 | J20: 投資 | K20: 財務 | L20: 営業 | M20: 投資 | N20: 財務 | O20: 営業 | P20: 投資 | Q20: 財務
B21: キャッシュフロー | C21: 28651 | D21: -29194 | E21: -4859 | F21: 16802 | G21: -20140 | H21: -10284 | I21: 28063 | J21: -8613 | K21: -6179 | L21: 1812 | M21: -10255 | N21: -39246 | O21: =IF(O48,O48,IF(L48,L48,IF(I48,I48,IF(F48,F48,IF(C48,C48,0))))) -> #VALUE! | P21: =IF(P48,P48,IF(M48,M48,IF(J48,J48,IF(G48,G48,IF(D48,D48,0))))) -> #VALUE! | Q21: =IF(Q48,Q48,IF(N48,N48,IF(K48,K48,IF(H48,H48,IF(E48,E48,0))))) -> #VALUE!
B22: 現金残／FCF | D22: 89463 | E22: =C21+D21 -> -543 | G22: 79917 | H22: =F21+G21 -> -3338 | J22: 94691 | K22: =I21+J21 -> 19450 | M22: 56610 | N22: =L21+M21 -> -8443 | P22: =IF(P49,P49,IF(M49,M49,IF(J49,J49,IF(G49,G49,IF(D49,D49,0))))) -> #VALUE! | Q22: =O21+P21 -> #VALUE!
C24: 資産価値 | D24: 事業価値 | E24: 理論株価 | F24: 資産価値 | G24: 事業価値 | H24: 理論株価 | I24: 資産価値 | J24: 事業価値 | K24: 理論株価 | L24: 資産価値 | M24: 事業価値 | N24: 理論株価 | O24: 資産価値 | P24: 事業価値 | Q24: 理論株価
B25: 理論株価 | C25: =D18*IF(C18>=0.8,0.8,IF(C18>=0.67,0.75,IF(C18>=0.5,0.7,IF(C18>=0.33,0.65,IF(C18>=0.1,0.6,0.5))))) -> 2641.8582 | D25: =IF(C19>0,IF(D10>0,IF(D14*C17,D14*(D10*0.7/C17*150),0),0)*C19,0) -> 1418.017 | E25: =C25+D25 -> 4059.8752 | F25: =G18*IF(F18>=0.8,0.8,IF(F18>=0.67,0.75,IF(F18>=0.5,0.7,IF(F18>=0.33,0.65,IF(F18>=0.1,0.6,0.5))))) -> 2502.3661 | G25: =IF(F19>0,IF(G10>0,IF(G14*F17,G14*(G10*0.7/F17*150),0),0)*F19,0) -> 545.35463 | H25: =F25+G25 -> 3047.7207 | I25: =J18*IF(I18>=0.8,0.8,IF(I18>=0.67,0.75,IF(I18>=0.5,0.7,IF(I18>=0.33,0.65,IF(I18>=0.1,0.6,0.5))))) -> 2690.0333 | J25: =IF(I19>0,IF(J10>0,IF(J14*I17,J14*(J10*0.7/I17*150),0),0)*I19,0) -> 1235.2909 | K25: =I25+J25 -> 3925.3242 | L25: =M18*IF(L18>=0.8,0.8,IF(L18>=0.67,0.75,IF(L18>=0.5,0.7,IF(L18>=0.33,0.65,IF(L18>=0.1,0.6,0.5))))) -> 2986.0446 | M25: =IF(L19>0,IF(M10>0,IF(M14*L17,M14*(M10*0.7/L17*150),0),0)*L19,0) -> 506.29481 | N25: =L25+M25 -> 3492.3394 | O25: =P18*IF(O18>=0.8,0.8,IF(O18>=0.67,0.75,IF(O18>=0.5,0.7,IF(O18>=0.33,0.65,IF(O18>=0.1,0.6,0.5))))) -> #VALUE! | P25: =IF(O19>0,IF(P10>0,IF(P14*O17,P14*(P10*0.7/O17*150),0),0)*O19,0) -> #VALUE! | Q25: =O25+P25 -> #VALUE!
B26: 株価／理論比 | C26: =DATE(LEFT(C4,4),LEFT(D4,LEN(D4)-2)+1,0) -> 44561 | E26: =IF(E25,D26/E25,0) -> 0 | F26: =DATE(LEFT(F4,4),LEFT(G4,LEN(G4)-2)+1,0) -> 44926 | H26: =IF(H25,G26/H25,0) -> 0 | I26: =DATE(LEFT(I4,4),LEFT(J4,LEN(J4)-2)+1,0) -> 45291 | K26: =IF(K25,J26/K25,0) -> 0 | L26: =DATE(LEFT(L4,4),LEFT(M4,LEN(M4)-2)+1,0) -> 45657 | N26: =IF(N25,M26/N25,0) -> 0 | O26: =IF(P53,O53,TODAY()) -> 46080 | P26: =IF(P53,P53,IF(M53,M53,IF(J53,J53,IF(G53,G53,IF(D53,D53,0))))) -> 0 | Q26: =IF(Q25,P26/Q25,0) -> #VALUE!
B27: 上限理論株価 | C27: =C25+(D25*2) -> 5477.8922 | F27: =F25+(G25*2) -> 3593.0753 | I27: =I25+(J25*2) -> 5160.6151 | L27: =L25+(M25*2) -> 3998.6342 | O27: =O25+(P25*2) -> #VALUE!
A28: ■今期会社予想
C29: 期初 | E29: 前期比 | F29: １Q | G29: =IF(G30>0,IF(G32>D32,"上方修正",IF(G32<D32,"下方修正","据え置き")),"") | H29: 前期比 | I29: ２Q | J29: =IF(J30>0,IF(J32>G32,"上方修正",IF(J32<G32,"下方修正","据え置き")),"") | K29: 前期比 | L29: ３Q | M29: =IF(M30>0,IF(M32>J32,"上方修正",IF(M32<J32,"下方修正","据え置き")),"") | N29: 前期比 | O29: 実績 | P29: =IF(P30>0,IF(P32>M32,"上方修正",IF(P32<M32,"下方修正","据え置き")),"") | Q29: 前期比
B30: 売上高 | E30: =IF($M5,D30/$M5,"-") -> 0 | H30: =IF($M5,G30/$M5,"-") -> 0 | K30: =IF($M5,J30/$M5,"-") -> 0 | N30: =IF($M5,M30/$M5,"-") -> 0 | Q30: =IF($M5,P30/$M5,"-") -> 0
B31: 経常利益 | E31: =IF($M10>0,D31/$M10,"-") -> 0 | H31: =IF($M10>0,G31/$M10,"-") -> 0 | K31: =IF($M10>0,J31/$M10,"-") -> 0 | N31: =IF($M10>0,M31/$M10,"-") -> 0 | Q31: =IF($M10>0,P31/$M10,"-") -> 0
B32: 純利益 | E32: =IF($M11>0,D32/$M11,"-") -> 0 | H32: =IF($M11>0,G32/$M11,"-") -> 0 | K32: =IF($M11>0,J32/$M11,"-") -> 0 | N32: =IF($M11>0,M32/$M11,"-") -> 0 | Q32: =IF($M11>0,P32/$M11,"-") -> 0
A34: ■今期四半期決算
C35: 期初 | E35: 前期比 | F35: １Q | H35: 進捗率 | I35: ２Q | K35: 進捗率 | L35: ３Q | N35: 進捗率 | O35: ４Q | Q35: 進捗率
B36: 売上高 | F36: =IF(F30,G36/F30,0) -> 0 | H36: =IF(G30,G36/G30,0) -> 0 | I36: =IF(I30,J36/I30,0) -> 0 | J36: データなし | K36: =IF(J30,J36/J30,0) -> 0 | N36: =IF(M30,M36/M30,0) -> 0 | Q36: =IF(P30,P36/P30,0) -> 0
B37: 経常利益 | F37: =IF(F31,G37/F31,0) -> 0 | H37: =IF(G31,G37/G31,0) -> 0 | I37: =IF(I31,J37/I31,0) -> 0 | J37: データなし | K37: =IF(J31,J37/J31,0) -> 0 | N37: =IF(M31,M37/M31,0) -> 0 | Q37: =IF(P31,P37/P31,0) -> 0
B38: 純利益 | F38: =IF(F32,G38/F32,0) -> 0 | H38: =IF(G32,G38/G32,0) -> 0 | I38: =IF(I32,J38/I32,0) -> 0 | J38: データなし | K38: =IF(J32,J38/J32,0) -> 0 | N38: =IF(M32,M38/M32,0) -> 0 | Q38: =IF(P32,P38/P32,0) -> 0
B40: 発行株数 | D40: =M13 -> 68468 | E40: 千株 | J40: 68468 | Q40: =N40 -> 0
B41: EPS／PER | D41: =IF(D40,D31*1000*0.7/D40,0) -> 0 | E41: =IF(D41,D53/D41,0) -> 0 | G41: =IF(G40,G31*1000*0.7/G40,0) -> 0 | H41: =IF(G41,G53/G41,0) -> 0 | J41: =IF(J40,J31*1000*0.7/J40,0) -> 0 | K41: =IF(J41,J53/J41,0) -> 0 | M41: =IF(M40,M31*1000*0.7/M40,0) -> 0 | N41: =IF(M41,M53/M41,0) -> 0 | P41: =IF(P40,P31*1000*0.7/P40,0) -> 0 | Q41: =IF(P41,P53/P41,0) -> 0
C43: 資産 | D43: 資本 | E43: 負債 | F43: 資産 | G43: 資本 | H43: 負債 | I43: 資産 | J43: 資本 | K43: 負債 | L43: 資産 | M43: 資本 | N43: 負債 | O43: 資産 | P43: 資本 | Q43: 負債
B44: バランスシート | C44: =L17 -> 377771 | D44: =M17 -> 272598 | E44: =C44-D44 -> 105173 | H44: =F44-G44 -> 0 | I44: データなし | J44: データなし | K44: =I44-J44 -> #VALUE! | N44: =L44-M44 -> 0 | Q44: =O44-P44 -> 0
B45: BPS／PBR | C45: =IF(C44,D44/C44,0) -> 0.72159589 | D45: =IF(D40,D44/D40*1000,0) -> 3981.3928 | E45: =IF(D45,D40/D45,0) -> 17.196997 | F45: =IF(F44,G44/F44,0) -> 0 | G45: =IF(G40,G44/G40*1000,0) -> 0 | H45: =IF(G45,G40/G45,0) -> 0 | I45: =IF(I44,J44/I44,0) -> #VALUE! | J45: =IF(J40,J44/J40*1000,0) -> #VALUE! | K45: =IF(J45,J40/J45,0) -> #VALUE! | L45: =IF(L44,M44/L44,0) -> 0 | M45: =IF(M40,M44/M40*1000,0) -> 0 | N45: =IF(M45,M40/M45,0) -> 0 | O45: =IF(O44,P44/O44,0) -> 0 | P45: =IF(P40,P44/P40*1000,0) -> 0 | Q45: =IF(P45,P40/P45,0) -> 0
B46: 財務レバレッジ補正 | C46: =IF(D44*C44>0,IF((1/(D44/C44+0.33))<1,1,IF((1/(D44/C44+0.33))>1.5,1.5,1/(D44/C44+0.33))),0) -> 1 | F46: =IF(G44*F44>0,IF((1/(G44/F44+0.33))<1,1,IF((1/(G44/F44+0.33))>1.5,1.5,1/(G44/F44+0.33))),0) -> 0 | I46: =IF(J44*I44>0,IF((1/(J44/I44+0.33))<1,1,IF((1/(J44/I44+0.33))>1.5,1.5,1/(J44/I44+0.33))),0) -> #VALUE! | L46: =IF(M44*L44>0,IF((1/(M44/L44+0.33))<1,1,IF((1/(M44/L44+0.33))>1.5,1.5,1/(M44/L44+0.33))),0) -> 0 | O46: =IF(P44*O44>0,IF((1/(P44/O44+0.33))<1,1,IF((1/(P44/O44+0.33))>1.5,1.5,1/(P44/O44+0.33))),0) -> 0
C47: 営業 | D47: 投資 | E47: 財務 | F47: 営業 | G47: 投資 | H47: 財務 | I47: 営業 | J47: 投資 | K47: 財務 | L47: 営業 | M47: 投資 | N47: 財務 | O47: 営業 | P47: 投資 | Q47: 財務
B48: キャッシュフロー | I48: データなし | J48: データなし | K48: データなし
B49: 現金残／FCF | D49: =M22 -> 56610 | E49: =C48+D48 -> 0 | H49: =F48+G48 -> 0 | J49: データなし | K49: =I48+J48 -> #VALUE! | N49: =L48+M48 -> 0 | Q49: =O48+P48 -> 0
C51: 資産価値 | D51: 事業価値 | E51: 理論株価 | F51: 資産価値 | G51: 事業価値 | H51: 理論株価 | I51: 資産価値 | J51: 事業価値 | K51: 理論株価 | L51: 資産価値 | M51: 事業価値 | N51: 理論株価 | O51: 資産価値 | P51: 事業価値 | Q51: 理論株価
B52: 理論株価 | C52: =D45*IF(C45>=0.8,0.8,IF(C45>=0.67,0.75,IF(C45>=0.5,0.7,IF(C45>=0.33,0.65,IF(C45>=0.1,0.6,0.5))))) -> 2986.0446 | D52: =IF(C46>0,IF(D31>0,IF(D41*C44,D41*(D31*0.7/C44*150),0),0)*C46,0) -> 0 | E52: =C52+D52 -> 2986.0446 | F52: =G45*IF(F45>=0.8,0.8,IF(F45>=0.67,0.75,IF(F45>=0.5,0.7,IF(F45>=0.33,0.65,IF(F45>=0.1,0.6,0.5))))) -> 0 | G52: =IF(F46>0,IF(G31>0,IF(G41*F44,G41*(G31*0.7/F44*150),0),0)*F46,0) -> 0 | H52: =F52+G52 -> 0 | I52: =J45*IF(I45>=0.8,0.8,IF(I45>=0.67,0.75,IF(I45>=0.5,0.7,IF(I45>=0.33,0.65,IF(I45>=0.1,0.6,0.5))))) -> #VALUE! | J52: =IF(I46>0,IF(J31>0,IF(J41*I44,J41*(J31*0.7/I44*150),0),0)*I46,0) -> #VALUE! | K52: =I52+J52 -> #VALUE! | L52: =M45*IF(L45>=0.8,0.8,IF(L45>=0.67,0.75,IF(L45>=0.5,0.7,IF(L45>=0.33,0.65,IF(L45>=0.1,0.6,0.5))))) -> 0 | M52: =IF(L46>0,IF(M31>0,IF(M41*L44,M41*(M31*0.7/L44*150),0),0)*L46,0) -> 0 | N52: =L52+M52 -> 0 | O52: =P45*IF(O45>=0.8,0.8,IF(O45>=0.67,0.75,IF(O45>=0.5,0.7,IF(O45>=0.33,0.65,IF(O45>=0.1,0.6,0.5))))) -> 0 | P52: =IF(O46>0,IF(P31>0,IF(P41*O44,P41*(P31*0.7/O44*150),0),0)*O46,0) -> 0 | Q52: =O52+P52 -> 0
B53: 株価／理論比 | C53: =L26 -> 45657 | D53: =M26 -> 0 | E53: =IF(E52,D53/E52,0) -> 0 | F53: =DATE(LEFT(O4,4),LEFT(P4,LEN(P4)-2)-8,0) -> 45747 | H53: =IF(H52,G53/H52,0) -> 0 | I53: =DATE(LEFT(O4,4),LEFT(P4,LEN(P4)-2)-5,0) -> 45838 | K53: =IF(K52,J53/K52,0) -> #VALUE! | L53: =DATE(LEFT(O4,4),LEFT(P4,LEN(P4)-2)-2,0) -> 45930 | N53: =IF(N52,M53/N52,0) -> 0 | O53: =DATE(LEFT(O4,4),LEFT(P4,LEN(P4)-2)+1,0) -> 46022 | Q53: =IF(Q52,P53/Q52,0) -> 0
B54: 上限理論株価 | C54: =C52+(D52*2) -> 2986.0446 | F54: =F52+(G52*2) -> 0 | I54: =I52+(J52*2) -> #VALUE! | L54: =L52+(M52*2) -> 0 | O54: =O52+(P52*2) -> 0
C56: 短期借 | D56: 長期借 | E56: 社債 | F56: 短期借 | G56: 長期借 | H56: 社債 | I56: 短期借 | J56: 長期借 | K56: 社債 | L56: 短期借 | M56: 長期借 | N56: 社債 | O56: 短期借 | P56: 長期借 | Q56: 社債
B57: 純有利子負債 | C57: データなし | D57: データなし | E57: データなし | F57: データなし | G57: データなし | H57: データなし | I57: データなし | J57: データなし | K57: データなし | L57: -26 | M57: データなし | N57: データなし | O57: データなし | P57: データなし | Q57: データなし
B58: 借金返済年数 | E58: =((C57+D57+E57)-D22)/E22 -> #VALUE! | H58: =((F57+G57+H57)-G22)/H22 -> #VALUE! | K58: =((I57+J57+K57)-J22)/K22 -> #VALUE! | N58: =((L57+M57+N57)-M22)/N22 -> #VALUE! | Q58: =((O57+P57+Q57)-P22)/Q22 -> #VALUE!
B60: 配当金 | D60: -7 | E60: =D60/E22 -> 0.012891344 | G60: -5002 | H60: =G60/H22 -> 1.4985021 | J60: -2 | K60: =J60/K22 -> -0.00010282776 | M60: -6 | N60: =M60/N22 -> 0.00071064787 | P60: データなし | Q60: =P60/Q22 -> #VALUE!
B61: 自己株式取得 | D61: -4545 | E61: =D61/E22 -> 8.3701657 | G61: -4816 | H61: =G61/H22 -> 1.4427801 | J61: -5087 | K61: =J61/K22 -> -0.26154242 | M61: -5405 | N61: =M61/N22 -> 0.64017529 | P61: データなし | Q61: =P61/Q22 -> #VALUE!
B63: 給与 | D63: データなし | G63: データなし | J63: データなし | M63: データなし
B64: 賞与 | D64: データなし | G64: データなし | J64: データなし | M64: データなし
B65: 賞与引当 | D65: データなし | G65: データなし | J65: データなし | M65: データなし
B66: 退職給付費用 | D66: 406 | G66: 272 | J66: 448 | M66: 189
B67: 減価償却費 | D67: 14249 | G67: 13896 | J67: 14016 | M67: 16754
B69: 目安 | E69: 借金返済目安
B70: 30〜50% → 健全 | E70: 年数 | F70: 評価
B71: 60〜70% → やや高め | E71: 0〜2年 | F71: 超健全
B72: 80%以上 → 危険信号 | E72: 3〜4年 | F72: 普通
B73: 100%以上 → 稼いだ以上に配っている | E73: 5年以上 | F73: やや重い
E74: 7年以上 | F74: 危険水域

Sheet 決算分析
K1: コード | L1: 銘柄名 | N1: 決算年 | O1: 決算月 | P1: 更新日
K2: =決算入力!K2 -> 2206 | L2: =決算入力!L2 -> 江崎グリコ株式会社 | N2: =決算入力!N2 -> 2025 | O2: =決算入力!O2 -> 12 | P2: =決算入力!P2 -> 46080.831
A3: ■時系列決算データ比較
C4: =LEFT(F4,4)-1&"年" -> 2021年 | D4: =G4 -> 12 月期 | E4: 構成比 | F4: =LEFT(I4,4)-1&"年" -> 2022年 | G4: =J4 -> 12 月期 | H4: 構成比 | I4: =LEFT(L4,4)-1&"年" -> 2023年 | J4: =M4 -> 12 月期 | K4: 構成比 | L4: =LEFT(O4,4)-1&"年" -> 2024年 | M4: =P4 -> 12 月期 | N4: 構成比 | O4: =N2 &" 年" -> 2025 年 | P4: =O2 &" 月期" -> 12 月期 | Q4: 構成比
B5: 売上高 | D5: =決算入力!D5 -> 338571 | E5: 百万 | G5: =決算入力!G5 -> 303921 | H5: =E5 -> 百万 | J5: =決算入力!J5 -> 332590 | K5: =E5 -> 百万 | M5: =決算入力!M5 -> 331129 | N5: =E5 -> 百万 | P5: =決算入力!P5 -> 0 | Q5: =H5 -> 百万
B6: 売上原価 | D6: =決算入力!D6 -> 180537 | E6: =IF(D$5,D6/D$5,"-") -> 0.53323232 | G6: =決算入力!G6 -> 193172 | H6: =IF(G$5,G6/G$5,"-") -> 0.63559938 | J6: =決算入力!J6 -> 208740 | K6: =IF(J$5,J6/J$5,"-") -> 0.62761959 | M6: =決算入力!M6 -> 203461 | N6: =IF(M$5,M6/M$5,"-") -> 0.61444633 | P6: =決算入力!P6 -> 0 | Q6: =IF(P$5,P6/P$5,"-") -> -
B7: 売上総利益 | D7: =決算入力!D7 -> 158033 | E7: =IF(D$5,D7/D$5,"-") -> 0.46676473 | G7: =決算入力!G7 -> 110749 | H7: =IF(G$5,G7/G$5,"-") -> 0.36440062 | J7: =決算入力!J7 -> 123850 | K7: =IF(J$5,J7/J$5,"-") -> 0.37238041 | M7: =決算入力!M7 -> 127668 | N7: =IF(M$5,M7/M$5,"-") -> 0.38555367 | P7: =決算入力!P7 -> 0 | Q7: =IF(P$5,P7/P$5,"-") -> -
B8: 販管費 | D8: =決算入力!D8 -> 138726 | E8: =IF(D$5,D8/D$5,"-") -> 0.40973976 | G8: =決算入力!G8 -> 97903 | H8: =IF(G$5,G8/G$5,"-") -> 0.32213305 | J8: =決算入力!J8 -> 105228 | K8: =IF(J$5,J8/J$5,"-") -> 0.31638955 | M8: =決算入力!M8 -> 116602 | N8: =IF(M$5,M8/M$5,"-") -> 0.35213467 | P8: =決算入力!P8 -> 0 | Q8: =IF(P$5,P8/P$5,"-") -> -
B9: 営業利益 | D9: =決算入力!D9 -> 19307 | E9: =IF(D$5,D9/D$5,"-") -> 0.057024967 | G9: =決算入力!G9 -> 12845 | H9: =IF(G$5,G9/G$5,"-") -> 0.042264273 | J9: =決算入力!J9 -> 18622 | K9: =IF(J$5,J9/J$5,"-") -> 0.05599086 | M9: =決算入力!M9 -> 11065 | N9: =IF(M$5,M9/M$5,"-") -> 0.03341598 | P9: =決算入力!P9 -> 0 | Q9: =IF(P$5,P9/P$5,"-") -> -
B10: 経常利益 | D10: =決算入力!D10 -> 21708 | E10: =IF(D$5,D10/D$5,"-") -> 0.064116537 | G10: =決算入力!G10 -> 13646 | H10: =IF(G$5,G10/G$5,"-") -> 0.044899826 | J10: =決算入力!J10 -> 21285 | K10: =IF(J$5,J10/J$5,"-") -> 0.063997715 | M10: =決算入力!M10 -> 13348 | N10: =IF(M$5,M10/M$5,"-") -> 0.040310574 | P10: =決算入力!P10 -> 0 | Q10: =IF(P$5,P10/P$5,"-") -> -
B11: 純利益 | D11: =決算入力!D11 -> 13567 | E11: =IF(D$5,D11/D$5,"-") -> 0.040071359 | G11: =決算入力!G11 -> 8156 | H11: =IF(G$5,G11/G$5,"-") -> 0.026835921 | J11: =決算入力!J11 -> 14219 | K11: =IF(J$5,J11/J$5,"-") -> 0.042752338 | M11: =決算入力!M11 -> 8157 | N11: =IF(M$5,M11/M$5,"-") -> 0.024633904 | P11: =決算入力!P11 -> 0 | Q11: =IF(P$5,P11/P$5,"-") -> -
B13: 発行株数 | D13: =決算入力!D13 -> 68468 | E13: 千株 | G13: =決算入力!G13 -> 68468 | H13: =E13 -> 千株 | J13: =決算入力!J13 -> 68468 | K13: =H13 -> 千株 | M13: =決算入力!M13 -> 68468 | N13: =K13 -> 千株 | P13: =決算入力!P13 -> 68468 | Q13: =N13 -> 千株
B14: ＥＰＳ／ＰＥＲ | D14: =決算入力!D14 -> 221.93726 | E14: =決算入力!E14 -> 0 | G14: =決算入力!G14 -> 139.51335 | H14: =決算入力!H14 -> 0 | J14: =決算入力!J14 -> 217.61261 | K14: =決算入力!K14 -> 0 | M14: =決算入力!M14 -> 136.46667 | N14: =決算入力!N14 -> 0 | P14: =決算入力!P14 -> 0 | Q14: =決算入力!Q14 -> 0
C16: 資産 | D16: 資本 | E16: 負債 | F16: 資産 | G16: 資本 | H16: 負債 | I16: 資産 | J16: 資本 | K16: 負債 | L16: 資産 | M16: 資本 | N16: 負債 | O16: 資産 | P16: 資本 | Q16: 負債
B17: バランスシート | C17: =決算入力!C17 -> 356745 | D17: =決算入力!D17 -> 241177 | E17: =C17-D17 -> 115568 | F17: =決算入力!F17 -> 369056 | G17: =決算入力!G17 -> 244760 | H17: =F17-G17 -> 124296 | I17: =決算入力!I17 -> 395743 | J17: =決算入力!J17 -> 263116 | K17: =I17-J17 -> 132627 | L17: =決算入力!L17 -> 377771 | M17: =決算入力!M17 -> 272598 | N17: =L17-M17 -> 105173 | O17: =決算入力!O17 -> #VALUE! | P17: =決算入力!P17 -> #VALUE! | Q17: =O17-P17 -> #VALUE!
B18: ＢＰＳ／ＰＢＲ | C18: =IF(C17,D17/C17,0) -> 0.67604872 | D18: =IF(D13,D17/D13*1000,0) -> 3522.4777 | E18: =決算入力!E18 -> 0 | F18: =IF(F17,G17/F17,0) -> 0.66320558 | G18: =IF(G13,G17/G13*1000,0) -> 3574.8087 | H18: =決算入力!H18 -> 0 | I18: =IF(I17,J17/I17,0) -> 0.66486583 | J18: =IF(J13,J17/J13*1000,0) -> 3842.9047 | K18: =決算入力!K18 -> 0 | L18: =IF(L17,M17/L17,0) -> 0.72159589 | M18: =IF(M13,M17/M13*1000,0) -> 3981.3928 | N18: =決算入力!N18 -> 0 | O18: =IF(O17,P17/O17,0) -> #VALUE! | P18: =IF(P13,P17/P13*1000,0) -> #VALUE! | Q18: =決算入力!Q18 -> #VALUE!
C19: =IF(D17*C17>0,IF((1/(D17/C17+0.33))<1,1,IF((1/(D17/C17+0.33))>1.5,1.5,1/(D17/C17+0.33))),0) -> 1 | F19: =IF(G17*F17>0,IF((1/(G17/F17+0.33))<1,1,IF((1/(G17/F17+0.33))>1.5,1.5,1/(G17/F17+0.33))),0) -> 1.0068409 | I19: =IF(J17*I17>0,IF((1/(J17/I17+0.33))<1,1,IF((1/(J17/I17+0.33))>1.5,1.5,1/(J17/I17+0.33))),0) -> 1.0051607 | L19: =IF(M17*L17>0,IF((1/(M17/L17+0.33))<1,1,IF((1/(M17/L17+0.33))>1.5,1.5,1/(M17/L17+0.33))),0) -> 1 | O19: =IF(P17*O17>0,IF((1/(P17/O17+0.33))<1,1,IF((1/(P17/O17+0.33))>1.5,1.5,1/(P17/O17+0.33))),0) -> #VALUE!
C20: 営業 | D20: 投資 | E20: 財務 | F20: 営業 | G20: 投資 | H20: 財務 | I20: 営業 | J20: 投資 | K20: 財務 | L20: 営業 | M20: 投資 | N20: 財務 | O20: 営業 | P20: 投資 | Q20: 財務
B21: キャッシュフロー | C21: =決算入力!C21 -> 28651 | D21: =決算入力!D21 -> -29194 | E21: =決算入力!E21 -> -4859 | F21: =決算入力!F21 -> 16802 | G21: =決算入力!G21 -> -20140 | H21: =決算入力!H21 -> -10284 | I21: =決算入力!I21 -> 28063 | J21: =決算入力!J21 -> -8613 | ... Q21: =決算入力!Q21 -> #VALUE!
B22: 現金残／ＦＣＦ | D22: =決算入力!D22 -> 89463 | E22: =決算入力!E22 -> -543 | G22: =決算入力!G22 -> 79917 | H22: =決算入力!H22 -> -3338 | J22: =決算入力!J22 -> 94691 | K22: =決算入力!K22 -> 19450 | M22: =決算入力!M22 -> 56610 | N22: =決算入力!N22 -> -8443 | P22: =決算入力!P22 -> #VALUE! | Q22: =決算入力!Q22 -> #VALUE!
A51: ■時系列比較データ
C52: 売上 | H52: 売上増収率 | L52: 前期比 | M52: 売上増収率 | Q52: ３期前比較
B53: 売上 | C53: ４期前 | D53: ３期前 | E53: ２期前 | F53: 前期 | G53: （今期） | H53: ４期前 | I53: ３期前 | J53: ２期前 | K53: 前期 | L53: （今期） | M53: ４期前 | N53: ３期前 | O53: ２期前 | P53: 前期 | Q53: （今期）
B54: =N2 -> 2025 | C54: =D5 -> 338571 | D54: =G5 -> 303921 | E54: =J5 -> 332590 | F54: =M5 -> 331129 | G54: =P5 -> 0 | H54: - | I54: =IF(C54,D54/C54,"-") -> 0.8976581 | J54: =IF(D54,E54/D54,"-") -> 1.0943304 | K54: =IF(E54,F54/E54,"-") -> 0.9956072 | L54: =IF(F54,G54/F54,"-") -> 0 | M54: =IF($C54,C54/$C54,"-") -> 1 | N54: =IF($C54,D54/$C54,"-") -> 0.8976581 | O54: =IF($C54,E54/$C54,"-") -> 0.98233458 | P54: =IF($C54,F54/$C54,"-") -> 0.97801938 | Q54: =IF($C54,G54/$C54,"-") -> 0
C56: 経常利益 | H56: 経常増益率 | L56: 前期比 | M56: 経常増益率 | Q56: ３期前比較
B57: 経常利益 | C57: ４期前 | D57: ３期前 | E57: ２期前 | F57: 前期 | G57: （今期） | H57: ４期前 | I57: ３期前 | J57: ２期前 | K57: 前期 | L57: （今期） | M57: ４期前 | N57: ３期前 | O57: ２期前 | P57: 前期 | Q57: （今期）
B58: =B$54 -> 2025 | C58: =D10 -> 21708 | D58: =G10 -> 13646 | E58: =J10 -> 21285 | F58: =M10 -> 13348 | G58: =P10 -> 0 | H58: - | I58: =IF(C58,D58/C58,"-") -> 0.62861618 | J58: =IF(D58,E58/D58,"-") -> 1.5597977 | K58: =IF(E58,F58/E58,"-") -> 0.62710829 | L58: =IF(F58,G58/F58,"-") -> 0 | M58: =IF($C58,C58/$C58,"-") -> 1 | N58: =IF($C58,D58/$C58,"-") -> 0.62861618 | O58: =IF($C58,E58/$C58,"-") -> 0.9805141 | P58: =IF($C58,F58/$C58,"-") -> 0.61488852 | Q58: =IF($C58,G58/$C58,"-") -> 0
C60: 株価 | H60: 株価上昇率 | L60: 前期比 | M60: 株価上昇率 | Q60: ３期前比較
B61: 株価 | C61: ４期前 | D61: ３期前 | E61: ２期前 | F61: 前期 | G61: （今期） | H61: ４期前 | I61: ３期前 | J61: ２期前 | K61: 前期 | L61: （今期） | M61: ４期前 | N61: ３期前 | O61: ２期前 | P61: 前期 | Q61: （今期）
B62: =B$54 -> 2025 | C62: =決算入力!D26 -> 0 | D62: =決算入力!G26 -> 0 | E62: =決算入力!J26 -> 0 | F62: =決算入力!M26 -> 0 | G62: =決算入力!P26 -> 0 | H62: - | I62: =IF(C62,D62/C62,"-") -> - | J62: =IF(D62,E62/D62,"-") -> - | K62: =IF(E62,F62/E62,"-") -> - | L62: =IF(F62,G62/F62,"-") -> - | M62: =IF($C62,C62/$C62,"-") -> - | N62: =IF($C62,D62/$C62,"-") -> - | O62: =IF($C62,E62/$C62,"-") -> - | P62: =IF($C62,F62/$C62,"-") -> - | Q62: =IF($C62,G62/$C62,"-") -> -
C64: 発行株数 | H64: 発行株数増加率 | L64: 前期比 | M64: 発行株数増加率 | Q64: ３期前比較
B65: 発行株数 | C65: ４期前 | D65: ３期前 | E65: ２期前 | F65: 前期 | G65: （今期） | H65: ４期前 | I65: ３期前 | J65: ２期前 | K65: 前期 | L65: （今期） | M65: ４期前 | N65: ３期前 | O65: ２期前 | P65: 前期 | Q65: （今期）
B66: =B$54 -> 2025 | C66: =D13 -> 68468 | D66: =G13 -> 68468 | E66: =J13 -> 68468 | F66: =M13 -> 68468 | G66: =P13 -> 68468 | H66: - | I66: =IF(C66,D66/C66,"-") -> 1 | J66: =IF(D66,E66/D66,"-") -> 1 | K66: =IF(E66,F66/E66,"-") -> 1 | L66: =IF(F66,G66/F66,"-") -> 1 | M66: =IF($C66,C66/$C66,"-") -> 1 | N66: =IF($C66,D66/$C66,"-") -> 1 | O66: =IF($C66,E66/$C66,"-") -> 1 | P66: =IF($C66,F66/$C66,"-") -> 1 | Q66: =IF($C66,G66/$C66,"-") -> 1
C68: 時価総額 | H68: 時価総額増加率 | L68: 前期比 | M68: 時価総額増加率 | Q68: ３期前比較
B69: 時価総額 | C69: ４期前 | D69: ３期前 | E69: ２期前 | F69: 前期 | G69: （今期） | H69: ４期前 | I69: ３期前 | J69: ２期前 | K69: 前期 | L69: （今期） | M69: ４期前 | N69: ３期前 | O69: ２期前 | P69: 前期 | Q69: （今期）
B70: =B$54 -> 2025 | C70: =C62*C66/1000 -> 0 | D70: =D62*D66/1000 -> 0 | E70: =E62*E66/1000 -> 0 | F70: =F62*F66/1000 -> 0 | G70: =G62*G66/1000 -> 0 | H70: - | I70: =IF(C70,D70/C70,0) -> 0 | J70: =IF(D70,E70/D70,0) -> 0 | K70: =IF(E70,F70/E70,0) -> 0 | L70: =IF(F70,G70/F70,0) -> 0 | M70: =IF($C70,C70/$C70,0) -> 0 | N70: =IF($C70,D70/$C70,0) -> 0 | O70: =IF($C70,E70/$C70,0) -> 0 | P70: =IF($C70,F70/$C70,0) -> 0 | Q70: =IF($C70,G70/$C70,0) -> 0
C72: ＥＰＳ | E72: (経常*30%) | H72: ＥＰＳ増加率 | L72: 前期比 | M72: ＥＰＳ増加率 | Q72: ３期前比較
B73: ＥＰＳ | C73: ４期前 | D73: ３期前 | E73: ２期前 | F73: 前期 | G73: （今期） | H73: ４期前 | I73: ３期前 | J73: ２期前 | K73: 前期 | L73: （今期） | M73: ４期前 | N73: ３期前 | O73: ２期前 | P73: 前期 | Q73: （今期）
B74: =B$54 -> 2025 | C74: =IF(C66,(C58*0.7)*1000/C66,0) -> 221.93726 | D74: =IF(D66,(D58*0.7)*1000/D66,0) -> 139.51335 | E74: =IF(E66,(E58*0.7)*1000/E66,0) -> 217.61261 | F74: =IF(F66,(F58*0.7)*1000/F66,0) -> 136.46667 | G74: =IF(G66,(G58*0.7)*1000/G66,0) -> 0 | H74: - | I74: =IF(C74,D74/C74,0) -> 0.62861618 | J74: =IF(D74,E74/D74,0) -> 1.5597977 | K74: =IF(E74,F74/E74,0) -> 0.62710829 | L74: =IF(F74,G74/F74,0) -> 0 | M74: =IF($C74,C74/$C74,0) -> 1 | N74: =IF($C74,D74/$C74,0) -> 0.62861618 | O74: =IF($C74,E74/$C74,0) -> 0.9805141 | P74: =IF($C74,F74/$C74,0) -> 0.61488852 | Q74: =IF($C74,G74/$C74,0) -> 0
C76: 現金残 | H76: 現金残増加率 | L76: 前期比 | M76: 現金残増加率 | Q76: ３期前比較
B77: 現金残 | C77: ４期前 | D77: ３期前 | E77: ２期前 | F77: 前期 | G77: （今期） | H77: ４期前 | I77: ３期前 | J77: ２期前 | K77: 前期 | L77: （今期） | M77: ４期前 | N77: ３期前 | O77: ２期前 | P77: 前期 | Q77: （今期）
B78: =B$54 -> 2025 | C78: =D22 -> 89463 | D78: =G22 -> 79917 | E78: =J22 -> 94691 | F78: =M22 -> 56610 | G78: =P22 -> #VALUE! | H78: - | I78: =IF(C78,D78/C78,0) -> 0.89329667 | J78: =IF(D78,E78/D78,0) -> 1.1848668 | K78: =IF(E78,F78/E78,0) -> 0.59783929 | L78: =IF(F78,G78/F78,0) -> #VALUE! | M78: =IF($C78,C78/$C78,0) -> 1 | N78: =IF($C78,D78/$C78,0) -> 0.89329667 | O78: =IF($C78,E78/$C78,0) -> 1.0584376 | P78: =IF($C78,F78/$C78,0) -> 0.63277556 | Q78: =IF($C78,G78/$C78,0) -> #VALUE!
C80: 売上原価 | H80: 粗利益 | L80: 前期比 | M80: 販管費 | Q80: ３期前比較
B81: ＰＬ | C81: ４期前 | D81: ３期前 | E81: ２期前 | F81: 前期 | G81: （今期） | H81: ４期前 | I81: ３期前 | J81: ２期前 | K81: 前期 | L81: （今期） | M81: ４期前 | N81: ３期前 | O81: ２期前 | P81: 前期 | Q81: （今期）
B82: =B$54 -> 2025 | C82: =D6 -> 180537 | D82: =G6 -> 193172 | E82: =J6 -> 208740 | F82: =M6 -> 203461 | G82: =P6 -> 0 | H82: =D7 -> 158033 | I82: =G7 -> 110749 | J82: =J7 -> 123850 | K82: =M7 -> 127668 | L82: =P7 -> 0 | M82: =D8 -> 138726 | N82: =G8 -> 97903 | O82: =J8 -> 105228 | P82: =M8 -> 116602 | Q82: =P8 -> 0
C84: 粗利益率 | H84: 販管費比率 | L84: 前期比 | M84: 経常利益率 | Q84: ３期前比較
B85: 利益率 | C85: ４期前 | D85: ３期前 | E85: ２期前 | F85: 前期 | G85: （今期） | H85: ４期前 | I85: ３期前 | J85: ２期前 | K85: 前期 | L85: （今期） | M85: ４期前 | N85: ３期前 | O85: ２期前 | P85: 前期 | Q85: （今期）
B86: =B$54 -> 2025 | C86: =H82/C54 -> 0.46676473 | D86: =I82/D54 -> 0.36440062 | E86: =J82/E54 -> 0.37238041 | F86: =K82/F54 -> 0.38555367 | G86: =L82/G54 -> #DIV/0! | H86: =M82/C54 -> 0.40973976 | I86: =N82/D54 -> 0.32213305 | J86: =O82/E54 -> 0.31638955 | K86: =P82/F54 -> 0.35213467 | L86: =Q82/G54 -> #DIV/0! | M86: =C58/C54 -> 0.064116537 | N86: =D58/D54 -> 0.044899826 | O86: =E58/E54 -> 0.063997715 | P86: =F58/F54 -> 0.040310574 | Q86: =G58/G54 -> #DIV/0!
C88: １株資産 | H88: １株資本 | M88: １株負債
B89: １株BS | C89: ４期前 | D89: ３期前 | E89: ２期前 | F89: 前期 | G89: （今期） | H89: ４期前 | I89: ３期前 | J89: ２期前 | K89: 前期 | L89: （今期） | M89: ４期前 | N89: ３期前 | O89: ２期前 | P89: 前期 | Q89: （今期）
B90: =B$54 -> 2025 | C90: =IF(D13,C17/D13*1000,0) -> 5210.3903 | D90: =IF(G13,F17/G13*1000,0) -> 5390.1969 | E90: =IF(J13,I17/J13*1000,0) -> 5779.9702 | F90: =IF(M13,L17/M13*1000,0) -> 5517.4826 | G90: =IF(P13,O17/P13*1000,0) -> #VALUE! | H90: =D18 -> 3522.4777 | I90: =G18 -> 3574.8087 | J90: =J18 -> 3842.9047 | K90: =M18 -> 3981.3928 | L90: =P18 -> #VALUE! | M90: =C90-H90 -> 1687.9126 | N90: =D90-I90 -> 1815.3882 | O90: =E90-J90 -> 1937.0655 | P90: =F90-K90 -> 1536.0899 | Q90: =G90-L90 -> #VALUE!
C92: ＲＯＡ | E92: (経常*30%) | H92: ＲＯＥ | J92: (経常*30%) | M92: 自己資本比率
B93: 収益効率 | C93: ４期前 | D93: ３期前 | E93: ２期前 | F93: 前期 | G93: （今期） | H93: ４期前 | I93: ３期前 | J93: ２期前 | K93: 前期 | L93: （今期） | M93: ４期前 | N93: ３期前 | O93: ２期前 | P93: 前期 | Q93: （今期）
B94: =B$54 -> 2025 | C94: =IF(C90,C74/C90,0) -> 0.042595131 | D94: =IF(D90,D74/D90,0) -> 0.025882793 | E94: =IF(E90,E74/E90,0) -> 0.037649434 | F94: =IF(F90,F74/F90,0) -> 0.024733503 | G94: =IF(G90,G74/G90,0) -> #VALUE! | H94: =IF(H90,C74/H90,0) -> 0.063006008 | I94: =IF(I90,D74/I90,0) -> 0.039026802 | J94: =IF(J90,E74/J90,0) -> 0.056627115 | K94: =IF(K90,F74/K90,0) -> 0.034276114 | L94: =IF(L90,G74/L90,0) -> #VALUE! | M94: =IF(C90,H90/C90,0) -> 0.67604872 | N94: =IF(D90,I90/D90,0) -> 0.66320558 | O94: =IF(E90,J90/E90,0) -> 0.66486583 | P94: =IF(F90,K90/F90,0) -> 0.72159589 | Q94: =IF(G90,L90/G90,0) -> #VALUE!
C96: 資産価値 | H96: 事業価値 | M96: 理論株価
B97: 理論株価 | C97: ４期前 | D97: ３期前 | E97: ２期前 | F97: 前期 | G97: （今期） | H97: ４期前 | I97: ３期前 | J97: ２期前 | K97: 前期 | L97: （今期） | M97: ４期前 | N97: ３期前 | O97: ２期前 | P97: 前期 | Q97: （今期）
B98: =B$54 -> 2025 | C98: =決算入力!C25 -> 2641.8582 | D98: =決算入力!F25 -> 2502.3661 | E98: =決算入力!I25 -> 2690.0333 | F98: =決算入力!L25 -> 2986.0446 | G98: =決算入力!O25 -> #VALUE! | H98: =決算入力!D25 -> 1418.017 | I98: =決算入力!G25 -> 545.35463 | J98: =決算入力!J25 -> 1235.2909 | K98: =決算入力!M25 -> 506.29481 | L98: =決算入力!P25 -> #VALUE! | M98: =決算入力!E25 -> 4059.8752 | N98: =決算入力!H25 -> 3047.7207 | O98: =決算入力!K25 -> 3925.3242 | P98: =決算入力!N25 -> 3492.3394 | Q98: =決算入力!Q25 -> #VALUE!
C100: ＰＢＲ | H100: 理論ＰＢＲ
B101: ＰＢＲ | C101: ４期前 | D101: ３期前 | E101: ２期前 | F101: 前期 | G101: （今期） | H101: ４期前 | I101: ３期前 | J101: ２期前 | K101: 前期 | L101: （今期）
B102: =B$54 -> 2025 | C102: =E18 -> 0 | D102: =H18 -> 0 | E102: =K18 -> 0 | F102: =N18 -> 0 | G102: =Q18 -> #VALUE! | H102: =IF(H90,M98/H90,0) -> 1.1525624 | I102: =IF(I90,N98/I90,0) -> 0.85255492 | J102: =IF(J90,O98/J90,0) -> 1.0214472 | K102: =IF(K90,P98/K90,0) -> 0.87716525 | L102: =IF(L90,Q98/L90,0) -> #VALUE!
C104: ＰＥＲ | E104: (経常*30%) | H104: 理論ＰＥＲ
B105: ＰＥＲ | C105: ４期前 | D105: ３期前 | E105: ２期前 | F105: 前期 | G105: （今期） | H105: ４期前 | I105: ３期前 | J105: ２期前 | K105: 前期 | L105: （今期）
B106: =B$54 -> 2025 | C106: =IF(C58,C70/(C58*0.7),0) -> 0 | D106: =IF(D58,D70/(D58*0.7),0) -> 0 | E106: =IF(E58,E70/(E58*0.7),0) -> 0 | F106: =IF(F58,F70/(F58*0.7),0) -> 0 | G106: =IF(G58,G70/(G58*0.7),0) -> 0 | H106: =IF(D14>0,M98/C74,0) -> 18.292896 | I106: =IF(G14>0,N98/G14,0) -> 21.84537 | J106: =IF(J14>0,O98/J14,0) -> 18.038129 | K106: =IF(M14>0,P98/M14,0) -> 25.591153 | L106: =IF(P14>0,Q98/P14,0) -> 0
C108: 営業ＣＦ | H108: 投資ＣＦ | M108: 財務ＣＦ
B109: １株ＣＦ | C109: ４期前 | D109: ３期前 | E109: ２期前 | F109: 前期 | G109: （今期） | H109: ４期前 | I109: ３期前 | J109: ２期前 | K109: 前期 | L109: （今期） | M109: ４期前 | N109: ３期前 | O109: ２期前 | P109: 前期 | Q109: （今期）
B110: =B$54 -> 2025 | C110: =IF(D13,C21/D13*1000,0) -> 418.45826 | D110: =IF(G13,F21/G13*1000,0) -> 245.39931 | E110: =IF(J13,I21/J13*1000,0) -> 409.8703 | F110: =IF(M13,L21/M13*1000,0) -> 26.464918 | G110: =IF(P13,O21/P13*1000,0) -> #VALUE! | H110: =IF(D13,D21/D13*1000,0) -> -426.38897 | I110: =IF(G13,G21/G13*1000,0) -> -294.15201 | J110: =IF(J13,J21/J13*1000,0) -> -125.79599 | K110: =IF(M13,M21/M13*1000,0) -> -149.778 | L110: =IF(P13,P21/P13*1000,0) -> #VALUE! | M110: =IF(D13,E21/D13*1000,0) -> -70.967459 | N110: =IF(G13,H21/G13*1000,0) -> -150.20155 | O110: =IF(J13,K21/J13*1000,0) -> -90.246539 | P110: =IF(M13,N21/M13*1000,0) -> -573.20208 | Q110: =IF(P13,Q21/P13*1000,0) -> #VALUE!
C112: ＦＣＦ | H112: ＰＣＦＲ | M112: 理論ＰＣＦＲ
B113: １株ＣＦ | C113: ４期前 | D113: ３期前 | E113: ２期前 | F113: 前期 | G113: （今期） | H113: ４期前 | I113: ３期前 | J113: ２期前 | K113: 前期 | L113: （今期） | M113: ４期前 | N113: ３期前 | O113: ２期前 | P113: 前期 | Q113: （今期）
B114: =B$54 -> 2025 | C114: =IF(D13,E22/D13*1000,0) -> -7.9307122 | D114: =IF(G13,H22/G13*1000,0) -> -48.752702 | E114: =IF(J13,K22/J13*1000,0) -> 284.07431 | F114: =IF(M13,N22/M13*1000,0) -> -123.31308 | G114: =IF(P13,Q22/P13*1000,0) -> #VALUE! | H114: =IF(C110,C62/C110,0) -> 0 | I114: =IF(D110,D62/D110,0) -> 0 | J114: =IF(E110,E62/E110,0) -> 0 | K114: =IF(F110,F62/F110,0) -> 0 | L114: =IF(G110,G62/G110,0) -> #VALUE! | M114: =IF(C110,M98/C110,0) -> 9.7019837 | N114: =IF(D110,N98/D110,0) -> 12.419435 | O114: =IF(E110,O98/E110,0) -> 9.576991 | P114: =IF(F110,P98/F110,0) -> 131.96109 | Q114: =IF(G110,Q98/G110,0) -> #VALUE!
C116: 金額 | H116: 増減率 | L116: 前期比 | M116: 増減率 | Q116: ３期前比較
B117: =B$54 -> 2025 | C117: ４期前 | D117: ３期前 | E117: ２期前 | F117: 前期 | G117: （今期） | H117: ４期前 | I117: ３期前 | J117: ２期前 | K117: 前期 | L117: （今期） | M117: ４期前 | N117: ３期前 | O117: ２期前 | P117: 前期 | Q117: （今期）
B118: 短期借入金 | C118: =決算入力!C$57 -> データなし | D118: =決算入力!F$57 -> データなし | E118: =決算入力!I$57 -> データなし | F118: =決算入力!L$57 -> -26 | G118: =決算入力!O$57 -> データなし | H118: - | I118: =IF(C118,D118/C118,"-") -> #VALUE! | J118: =IF(D118,E118/D118,"-") -> #VALUE! | K118: =IF(E118,F118/E118,"-") -> #VALUE! | L118: =IF(F118,G118/F118,"-") -> #VALUE! | M118: =IF($C118,C118/$C118,"-") -> #VALUE! | N118: =IF($C118,D118/$C118,"-") -> #VALUE! | O118: =IF($C118,E118/$C118,"-") -> #VALUE! | P118: =IF($C118,F118/$C118,"-") -> #VALUE! | Q118: =IF($C118,G118/$C118,"-") -> #VALUE!
B119: 長期借入金 | C119: =決算入力!D$57 -> データなし | D119: =決算入力!G$57 -> データなし | E119: =決算入力!J$57 -> データなし | F119: =決算入力!M$57 -> データなし | G119: =決算入力!P$57 -> データなし | H119: - | I119: =IF(C119,D119/C119,"-") -> #VALUE! | J119: =IF(D119,E119/D119,"-") -> #VALUE! | K119: =IF(E119,F119/E119,"-") -> #VALUE! | L119: =IF(F119,G119/F119,"-") -> #VALUE! | M119: =IF($C119,C119/$C119,"-") -> #VALUE! | N119: =IF($C119,D119/$C119,"-") -> #VALUE! | O119: =IF($C119,E119/$C119,"-") -> #VALUE! | P119: =IF($C119,F119/$C119,"-") -> #VALUE! | Q119: =IF($C119,G119/$C119,"-") -> #VALUE!
B120: 社債 | C120: =決算入力!E$57 -> データなし | D120: =決算入力!H$57 -> データなし | E120: =決算入力!K$57 -> データなし | F120: =決算入力!N$57 -> データなし | G120: =決算入力!Q$57 -> データなし | H120: - | I120: =IF(C120,D120/C120,"-") -> #VALUE! | J120: =IF(D120,E120/D120,"-") -> #VALUE! | K120: =IF(E120,F120/E120,"-") -> #VALUE! | L120: =IF(F120,G120/F120,"-") -> #VALUE! | M120: =IF($C120,C120/$C120,"-") -> #VALUE! | N120: =IF($C120,D120/$C120,"-") -> #VALUE! | O120: =IF($C120,E120/$C120,"-") -> #VALUE! | P120: =IF($C120,F120/$C120,"-") -> #VALUE! | Q120: =IF($C120,G120/$C120,"-") -> #VALUE!
B121: 純利子負債 | C121: =SUM(C118:C120) -> 0 | D121: =SUM(D118:D120) -> 0 | E121: =SUM(E118:E120) -> 0 | F121: =SUM(F118:F120) -> -26 | G121: =SUM(G118:G120) -> 0 | H121: - | I121: =IF(C121,D121/C121,"-") -> - | J121: =IF(D121,E121/D121,"-") -> - | K121: =IF(E121,F121/E121,"-") -> - | L121: =IF(F121,G121/F121,"-") -> 0 | M121: =IF($C121,C121/$C121,"-") -> - | N121: =IF($C121,D121/$C121,"-") -> - | O121: =IF($C121,E121/$C121,"-") -> - | P121: =IF($C121,F121/$C121,"-") -> - | Q121: =IF($C121,G121/$C121,"-") -> -
C123: 借金返済年数 (純利子負債/(営業利益+CF減価償却費))
B124: 借金返済年数 | C124: ４期前 | D124: ３期前 | E124: ２期前 | F124: 前期 | G124: （今期）
B125: =B$54 -> 2025 | C125: =C121/(D9+決算入力!D67) -> 0 | D125: =D121/(G9+決算入力!G67) -> 0 | E125: =E121/(J9+決算入力!J67) -> 0 | F125: =F121/(M9+決算入力!M67) -> -0.00093461303 | G125: =G121/(P9+決算入力!P67) -> #DIV/0!
C127: 配当金 | H127: 配当金性向 (配当金/FCF) | M127: 配当金性向 (配当金/純利益)
B128: 配当金 | C128: ４期前 | D128: ３期前 | E128: ２期前 | F128: 前期 | G128: （今期） | H128: ４期前 | I128: ３期前 | J128: ２期前 | K128: 前期 | L128: （今期） | M128: ４期前 | N128: ３期前 | O128: ２期前 | P128: 前期 | Q128: （今期）
B129: =B$54 -> 2025 | C129: =決算入力!D60 -> -7 | D129: =決算入力!G60 -> -5002 | E129: =決算入力!J60 -> -2 | F129: =決算入力!M60 -> -6 | G129: =決算入力!P60 -> データなし | H129: =$C$129/決算入力!E$22 -> 0.012891344 | I129: =$D$129/決算入力!H$22 -> 1.4985021 | J129: =$E$129/決算入力!K$22 -> -0.00010282776 | K129: =$F$129/決算入力!N$22 -> 0.00071064787 | L129: =$G$129/決算入力!Q$22 -> #VALUE! | M129: =$C$129/D$11 -> -0.00051595784 | N129: =$D$129/G$11 -> -0.61329083 | O129: =$E$129/J$11 -> -0.00014065687 | P129: =$F$129/M$11 -> -0.00073556455 | Q129: =$G$129/P$11 -> #VALUE!
C130: 金額 | H130: 増減率 | L130: 前期比 | M130: 増減率 | Q130: ３期前比較
B131: 自己株式取得 | C131: ４期前 | D131: ３期前 | E131: ２期前 | F131: 前期 | G131: （今期） | H131: ４期前 | I131: ３期前 | J131: ２期前 | K131: 前期 | L131: （今期） | M131: ４期前 | N131: ３期前 | O131: ２期前 | P131: 前期 | Q131: （今期）
B132: =B$54 -> 2025 | C132: =決算入力!D61 -> -4545 | D132: =決算入力!G61 -> -4816 | E132: =決算入力!J61 -> -5087 | F132: =決算入力!M61 -> -5405 | G132: =決算入力!P61 -> データなし | H132: - | I132: =IF(C132,D132/C132,"-") -> 1.059626 | J132: =IF(D132,E132/D132,"-") -> 1.0562708 | K132: =IF(E132,F132/E132,"-") -> 1.0625123 | L132: =IF(F132,G132/F132,"-") -> #VALUE! | M132: =IF($C132,C132/$C132,"-") -> 1 | N132: =IF($C132,D132/$C132,"-") -> 1.059626 | O132: =IF($C132,E132/$C132,"-") -> 1.1192519 | P132: =IF($C132,F132/$C132,"-") -> 1.1892189 | Q132: =IF($C132,G132/$C132,"-") -> #VALUE!
C133: 還元額 | H133: 還元率 (還元額/FCF) | M133: 還元率 (還元額/期末残高)
B134: 株主還元 | C134: ４期前 | D134: ３期前 | E134: ２期前 | F134: 前期 | G134: （今期） | H134: ４期前 | I134: ３期前 | J134: ２期前 | K134: 前期 | L134: （今期） | M134: ４期前 | N134: ３期前 | O134: ２期前 | P134: 前期 | Q134: （今期）
B135: =B$54 -> 2025 | C135: =C129+C132 -> -4552 | D135: =D129+D132 -> -9818 | E135: =E129+E132 -> -5089 | F135: =F129+F132 -> -5411 | G135: =G129+G132 -> #VALUE! | H135: =C135/決算入力!E$22 -> 8.3830571 | I135: =D135/決算入力!H$22 -> 2.9412822 | J135: =E135/決算入力!K$22 -> -0.26164524 | K135: =F135/決算入力!N$22 -> 0.64088594 | L135: =G135/決算入力!Q$22 -> #VALUE! | M135: =C135/決算入力!D$22 -> -0.05088137 | N135: =D135/決算入力!G$22 -> -0.12285246 | O135: =E135/決算入力!J$22 -> -0.053743228 | P135: =F135/決算入力!M$22 -> -0.095583819 | Q135: =G135/決算入力!P$22 -> #VALUE!
C137: 還元額 | H137: 還元率 (還元額/FCF) | M137: 還元率 (還元額/期末残高)
B138: 従業員還元 | C138: ４期前 | D138: ３期前 | E138: ２期前 | F138: 前期 | G138: （今期） | H138: ４期前 | I138: ３期前 | J138: ２期前 | K138: 前期 | L138: （今期） | M138: ４期前 | N138: ３期前 | O138: ２期前 | P138: 前期 | Q138: （今期）
B139: =B$54 -> 2025 | C139: =SUM(決算入力!D$63:D$67) -> 14655 | D139: =SUM(決算入力!G$63:G$67) -> 14168 | E139: =SUM(決算入力!J$63:J$67) -> 14464 | F139: =SUM(決算入力!M$63:M$67) -> 16943 | G139: =SUM(決算入力!P$63:P$67) -> 0 | H139: =C139/決算入力!E$22 -> -26.98895 | I139: =D139/決算入力!H$22 -> -4.2444578 | J139: =E139/決算入力!K$22 -> 0.74365039 | K139: =F139/決算入力!N$22 -> -2.0067512 | L139: =G139/決算入力!Q$22 -> #VALUE! | M139: =C139/決算入力!D$22 -> 0.16381074 | N139: =D139/決算入力!G$22 -> 0.17728393 | O139: =E139/決算入力!J$22 -> 0.15274947 | P139: =F139/決算入力!M$22 -> 0.29929341 | Q139: =G139/決算入力!P$22 -> #VALUE!
C141: FCF基準 (株主還元額/(営業利益+株主還元額+CF減価償却費)
B142: 付加価値分配率 | C142: ４期前 | D142: ３期前 | E142: ２期前 | F142: 前期 | G142: （今期）
B143: =B$54 -> 2025 | C143: =C139/(D9+C139+決算入力!D67) -> 0.30397627 | D143: =D139/(G9+D139+決算入力!G67) -> 0.34632966 | E143: =E139/(J9+E139+決算入力!J67) -> 0.30707826 | F143: =F139/(M9+F139+決算入力!M67) -> 0.37851302 | G143: =G139/(P9+G139+決算入力!P67) -> #DIV/0!

Sheet メモ
A1: ・ | B1: 増減率について
B2: 赤字から黒字になった場合：-(ハイフン)
B3: 黒字から赤字になった場合：-(ハイフン)
B4: 0から増減した場合：-(ハイフン)

Sheet 決算入力 (2)
K1: コード | L1: 銘柄名 | N1: 決算年 | O1: 決算月 | P1: 更新日
P2: =NOW() -> 46080.831
A3: ■時系列決算データ比較
C4: =LEFT(F4,4)-1&"年" -> #VALUE! | D4: =G4 -> 月期 | E4: 構成比 | F4: =LEFT(I4,4)-1&"年" -> #VALUE! | G4: =J4 -> 月期 | H4: 構成比 | I4: =LEFT(L4,4)-1&"年" -> #VALUE! | J4: =M4 -> 月期 | K4: 構成比 | L4: =LEFT(O4,4)-1&"年" -> #VALUE! | M4: =P4 -> 月期 | N4: 構成比 | O4: =N2 &" 年" -> 年 | P4: =O2 &" 月期" -> 月期 | Q4: 構成比
B5: 売上高 | E5: 百万 | H5: =E5 -> 百万 | K5: =E5 -> 百万 | N5: =E5 -> 百万 | P5: =IF(P30,P30,IF(M30,M30,IF(J30,J30,IF(G30,G30,IF(D30,D30,0))))) -> 0 | Q5: =H5 -> 百万
B6: 売上原価 | E6: =IF(D$5,D6/D$5,"-") -> - | H6: =IF(G$5,G6/G$5,"-") -> - | K6: =IF(J$5,J6/J$5,"-") -> - | N6: =IF(M$5,M6/M$5,"-") -> - | Q6: =IF(P$5,P6/P$5,"-") -> -
B7: 売上総利益 | E7: =IF(D$5,D7/D$5,"-") -> - | H7: =IF(G$5,G7/G$5,"-") -> - | K7: =IF(J$5,J7/J$5,"-") -> - | N7: =IF(M$5,M7/M$5,"-") -> - | Q7: =IF(P$5,P7/P$5,"-") -> -
B8: 販管費 | E8: =IF(D$5,D8/D$5,"-") -> - | H8: =IF(G$5,G8/G$5,"-") -> - | K8: =IF(J$5,J8/J$5,"-") -> - | N8: =IF(M$5,M8/M$5,"-") -> - | Q8: =IF(P$5,P8/P$5,"-") -> -
B9: 営業利益 | E9: =IF(D$5,D9/D$5,"-") -> - | H9: =IF(G$5,G9/G$5,"-") -> - | K9: =IF(J$5,J9/J$5,"-") -> - | N9: =IF(M$5,M9/M$5,"-") -> - | Q9: =IF(P$5,P9/P$5,"-") -> -
B10: 経常利益 | E10: =IF(D$5,D10/D$5,"-") -> - | H10: =IF(G$5,G10/G$5,"-") -> - | K10: =IF(J$5,J10/J$5,"-") -> - | N10: =IF(M$5,M10/M$5,"-") -> - | P10: =IF(P31,P31,IF(M31,M31,IF(J31,J31,IF(G31,G31,IF(D31,D31,0))))) -> 0 | Q10: =IF(P$5,P10/P$5,"-") -> -
B11: 純利益 | E11: =IF(D$5,D11/D$5,"-") -> - | H11: =IF(G$5,G11/G$5,"-") -> - | K11: =IF(J$5,J11/J$5,"-") -> - | N11: =IF(M$5,M11/M$5,"-") -> - | P11: =IF(P32,P32,IF(M32,M32,IF(J32,J32,IF(G32,G32,IF(D32,D32,0))))) -> 0 | Q11: =IF(P$5,P11/P$5,"-") -> -
B13: 発行株数 | E13: 千株 | H13: =E13 -> 千株 | K13: =H13 -> 千株 | N13: =K13 -> 千株 | P13: =IF(P40,P40,IF(M40,M40,IF(J40,J40,IF(G40,G40,IF(D40,D40,0))))) -> 0 | Q13: =N13 -> 千株
B14: EPS／PER | D14: =IF(D13,D10*1000*0.7/D13,0) -> 0 | E14: =IF(D14,D26/D14,0) -> 0 | G14: =IF(G13,G10*1000*0.7/G13,0) -> 0 | H14: =IF(G14,G26/G14,0) -> 0 | J14: =IF(J13,J10*1000*0.7/J13,0) -> 0 | K14: =IF(J14,J26/J14,0) -> 0 | M14: =IF(M13,M10*1000*0.7/M13,0) -> 0 | N14: =IF(M14,M26/M14,0) -> 0 | P14: =IF(P13,P10*1000*0.7/P13,0) -> 0 | Q14: =IF(P14,P26/P14,0) -> 0
C16: 資産 | D16: 資本 | E16: 負債 | F16: 資産 | G16: 資本 | H16: 負債 | I16: 資産 | J16: 資本 | K16: 負債 | L16: 資産 | M16: 資本 | N16: 負債 | O16: 資産 | P16: 資本 | Q16: 負債
B17: バランスシート | E17: =C17-D17 -> 0 | H17: =F17-G17 -> 0 | K17: =I17-J17 -> 0 | N17: =L17-M17 -> 0 | O17: =IF(O44,O44,IF(L44,L44,IF(I44,I44,IF(F44,F44,IF(C44,C44,0))))) -> 0 | P17: =IF(P44,P44,IF(M44,M44,IF(J44,J44,IF(G44,G44,IF(D44,D44,0))))) -> 0 | Q17: =O17-P17 -> 0
B18: BPS／PBR | C18: =IF(C17,D17/C17,0) -> 0 | D18: =IF(D13,D17/D13*1000,0) -> 0 | E18: =IF(D18,D26/D18,0) -> 0 | F18: =IF(F17,G17/F17,0) -> 0 | G18: =IF(G13,G17/G13*1000,0) -> 0 | H18: =IF(G18,G26/G18,0) -> 0 | I18: =IF(I17,J17/I17,0) -> 0 | J18: =IF(J13,J17/J13*1000,0) -> 0 | K18: =IF(J18,J26/J18,0) -> 0 | L18: =IF(L17,M17/L17,0) -> 0 | M18: =IF(M13,M17/M13*1000,0) -> 0 | N18: =IF(M18,M26/M18,0) -> 0 | O18: =IF(O17,P17/O17,0) -> 0 | P18: =IF(P13,P17/P13*1000,0) -> 0 | Q18: =IF(P18,P26/P18,0) -> 0
B19: 財務レバレッジ補正 | C19: =IF(D17*C17>0,IF((1/(D17/C17+0.33))<1,1,IF((1/(D17/C17+0.33))>1.5,1.5,1/(D17/C17+0.33))),0) -> 0 | F19: =IF(G17*F17>0,IF((1/(G17/F17+0.33))<1,1,IF((1/(G17/F17+0.33))>1.5,1.5,1/(G17/F17+0.33))),0) -> 0 | I19: =IF(J17*I17>0,IF((1/(J17/I17+0.33))<1,1,IF((1/(J17/I17+0.33))>1.5,1.5,1/(J17/I17+0.33))),0) -> 0 | L19: =IF(M17*L17>0,IF((1/(M17/L17+0.33))<1,1,IF((1/(M17/L17+0.33))>1.5,1.5,1/(M17/L17+0.33))),0) -> 0 | O19: =IF(P17*O17>0,IF((1/(P17/O17+0.33))<1,1,IF((1/(P17/O17+0.33))>1.5,1.5,1/(P17/O17+0.33))),0) -> 0
C20: 営業 | D20: 投資 | E20: 財務 | F20: 営業 | G20: 投資 | H20: 財務 | I20: 営業 | J20: 投資 | K20: 財務 | L20: 営業 | M20: 投資 | N20: 財務 | O20: 営業 | P20: 投資 | Q20: 財務
B21: キャッシュフロー | O21: =IF(O48,O48,IF(L48,L48,IF(I48,I48,IF(F48,F48,IF(C48,C48,0))))) -> 0 | P21: =IF(P48,P48,IF(M48,M48,IF(J48,J48,IF(G48,G48,IF(D48,D48,0))))) -> 0 | Q21: =IF(Q48,Q48,IF(N48,N48,IF(K48,K48,IF(H48,H48,IF(E48,E48,0))))) -> 0
B22: 現金残／FCF | E22: =C21+D21 -> 0 | H22: =F21+G21 -> 0 | K22: =I21+J21 -> 0 | N22: =L21+M21 -> 0 | P22: =IF(P49,P49,IF(M49,M49,IF(J49,J49,IF(G49,G49,IF(D49,D49,0))))) -> 0 | Q22: =O21+P21 -> 0
C24: 資産価値 | D24: 事業価値 | E24: 理論株価 | F24: 資産価値 | G24: 事業価値 | H24: 理論株価 | I24: 資産価値 | J24: 事業価値 | K24: 理論株価 | L24: 資産価値 | M24: 事業価値 | N24: 理論株価 | O24: 資産価値 | P24: 事業価値 | Q24: 理論株価
B25: 理論株価 | C25: =D18*IF(C18>=0.8,0.8,IF(C18>=0.67,0.75,IF(C18>=0.5,0.7,IF(C18>=0.33,0.65,IF(C18>=0.1,0.6,0.5))))) -> 0 | D25: =IF(C19>0,IF(D10>0,IF(D14*C17,D14*(D10*0.7/C17*150),0),0)*C19,0) -> 0 | E25: =C25+D25 -> 0 | F25: =G18*IF(F18>=0.8,0.8,IF(F18>=0.67,0.75,IF(F18>=0.5,0.7,IF(F18>=0.33,0.65,IF(F18>=0.1,0.6,0.5))))) -> 0 | G25: =IF(F19>0,IF(G10>0,IF(G14*F17,G14*(G10*0.7/F17*150),0),0)*F19,0) -> 0 | H25: =F25+G25 -> 0 | I25: =J18*IF(I18>=0.8,0.8,IF(I18>=0.67,0.75,IF(I18>=0.5,0.7,IF(I18>=0.33,0.65,IF(I18>=0.1,0.6,0.5))))) -> 0 | J25: =IF(I19>0,IF(J10>0,IF(J14*I17,J14*(J10*0.7/I17*150),0),0)*I19,0) -> 0 | K25: =I25+J25 -> 0 | L25: =M18*IF(L18>=0.8,0.8,IF(L18>=0.67,0.75,IF(L18>=0.5,0.7,IF(L18>=0.33,0.65,IF(L18>=0.1,0.6,0.5))))) -> 0 | M25: =IF(L19>0,IF(M10>0,IF(M14*L17,M14*(M10*0.7/L17*150),0),0)*L19,0) -> 0 | N25: =L25+M25 -> 0 | O25: =P18*IF(O18>=0.8,0.8,IF(O18>=0.67,0.75,IF(O18>=0.5,0.7,IF(O18>=0.33,0.65,IF(O18>=0.1,0.6,0.5))))) -> 0 | P25: =IF(O19>0,IF(P10>0,IF(P14*O17,P14*(P10*0.7/O17*150),0),0)*O19,0) -> 0 | Q25: =O25+P25 -> 0
B26: 株価／理論比 | C26: =DATE(LEFT(C4,4),LEFT(D4,LEN(D4)-2)+1,0) -> #VALUE! | E26: =IF(E25,D26/E25,0) -> 0 | F26: =DATE(LEFT(F4,4),LEFT(G4,LEN(G4)-2)+1,0) -> #VALUE! | H26: =IF(H25,G26/H25,0) -> 0 | I26: =DATE(LEFT(I4,4),LEFT(J4,LEN(J4)-2)+1,0) -> #VALUE! | K26: =IF(K25,J26/K25,0) -> 0 | L26: =DATE(LEFT(L4,4),LEFT(M4,LEN(M4)-2)+1,0) -> #VALUE! | N26: =IF(N25,M26/N25,0) -> 0 | O26: =IF(P53,O53,TODAY()) -> 46080 | P26: =IF(P53,P53,IF(M53,M53,IF(J53,J53,IF(G53,G53,IF(D53,D53,0))))) -> 0 | Q26: =IF(Q25,P26/Q25,0) -> 0
B27: 上限理論株価 | C27: =C25+(D25*2) -> 0 | F27: =F25+(G25*2) -> 0 | I27: =I25+(J25*2) -> 0 | L27: =L25+(M25*2) -> 0 | O27: =O25+(P25*2) -> 0
A28: ■今期会社予想
C29: 期初 | E29: 前期比 | F29: １Q | G29: =IF(G30>0,IF(G32>D32,"上方修正",IF(G32<D32,"下方修正","据え置き")),"") | H29: 前期比 | I29: ２Q | J29: =IF(J30>0,IF(J32>G32,"上方修正",IF(J32<G32,"下方修正","据え置き")),"") | K29: 前期比 | L29: ３Q | M29: =IF(M30>0,IF(M32>J32,"上方修正",IF(M32<J32,"下方修正","据え置き")),"") | N29: 前期比 | O29: 実績 | P29: =IF(P30>0,IF(P32>M32,"上方修正",IF(P32<M32,"下方修正","据え置き")),"") | Q29: 前期比
B30: 売上高 | E30: =IF($M5,D30/$M5,"-") -> - | H30: =IF($M5,G30/$M5,"-") -> - | K30: =IF($M5,J30/$M5,"-") -> - | N30: =IF($M5,M30/$M5,"-") -> - | Q30: =IF($M5,P30/$M5,"-") -> -
B31: 経常利益 | E31: =IF($M10>0,D31/$M10,"-") -> - | H31: =IF($M10>0,G31/$M10,"-") -> - | K31: =IF($M10>0,J31/$M10,"-") -> - | N31: =IF($M10>0,M31/$M10,"-") -> - | Q31: =IF($M10>0,P31/$M10,"-") -> -
B32: 純利益 | E32: =IF($M11>0,D32/$M11,"-") -> - | H32: =IF($M11>0,G32/$M11,"-") -> - | K32: =IF($M11>0,J32/$M11,"-") -> - | N32: =IF($M11>0,M32/$M11,"-") -> - | Q32: =IF($M11>0,P32/$M11,"-") -> -
A34: ■今期四半期決算
C35: 期初 | E35: 前期比 | F35: １Q | H35: 進捗率 | I35: ２Q | K35: 進捗率 | L35: ３Q | N35: 進捗率 | O35: ４Q | Q35: 進捗率
B36: 売上高 | F36: =IF(F30,G36/F30,0) -> 0 | H36: =IF(G30,G36/G30,0) -> 0 | I36: =IF(I30,J36/I30,0) -> 0 | K36: =IF(J30,J36/J30,0) -> 0 | N36: =IF(M30,M36/M30,0) -> 0 | Q36: =IF(P30,P36/P30,0) -> 0
B37: 経常利益 | F37: =IF(F31,G37/F31,0) -> 0 | H37: =IF(G31,G37/G31,0) -> 0 | I37: =IF(I31,J37/I31,0) -> 0 | K37: =IF(J31,J37/J31,0) -> 0 | N37: =IF(M31,M37/M31,0) -> 0 | Q37: =IF(P31,P37/P31,0) -> 0
B38: 純利益 | F38: =IF(F32,G38/F32,0) -> 0 | H38: =IF(G32,G38/G32,0) -> 0 | I38: =IF(I32,J38/I32,0) -> 0 | K38: =IF(J32,J38/J32,0) -> 0 | N38: =IF(M32,M38/M32,0) -> 0 | Q38: =IF(P32,P38/P32,0) -> 0
B40: 発行株数 | D40: =M13 -> 0 | E40: 千株 | Q40: =N40 -> 0
B41: EPS／PER | D41: =IF(D40,D31*1000*0.7/D40,0) -> 0 | E41: =IF(D41,D53/D41,0) -> 0 | G41: =IF(G40,G31*1000*0.7/G40,0) -> 0 | H41: =IF(G41,G53/G41,0) -> 0 | J41: =IF(J40,J31*1000*0.7/J40,0) -> 0 | K41: =IF(J41,J53/J41,0) -> 0 | M41: =IF(M40,M31*1000*0.7/M40,0) -> 0 | N41: =IF(M41,M53/M41,0) -> 0 | P41: =IF(P40,P31*1000*0.7/P40,0) -> 0 | Q41: =IF(P41,P53/P41,0) -> 0
C43: 資産 | D43: 資本 | E43: 負債 | F43: 資産 | G43: 資本 | H43: 負債 | I43: 資産 | J43: 資本 | K43: 負債 | L43: 資産 | M43: 資本 | N43: 負債 | O43: 資産 | P43: 資本 | Q43: 負債
B44: バランスシート | C44: =L17 -> 0 | D44: =M17 -> 0 | E44: =C44-D44 -> 0 | H44: =F44-G44 -> 0 | K44: =I44-J44 -> 0 | N44: =L44-M44 -> 0 | Q44: =O44-P44 -> 0
B45: BPS／PBR | C45: =IF(C44,D44/C44,0) -> 0 | D45: =IF(D40,D44/D40*1000,0) -> 0 | E45: =IF(D45,D40/D45,0) -> 0 | F45: =IF(F44,G44/F44,0) -> 0 | G45: =IF(G40,G44/G40*1000,0) -> 0 | H45: =IF(G45,G40/G45,0) -> 0 | I45: =IF(I44,J44/I44,0) -> 0 | J45: =IF(J40,J44/J40*1000,0) -> 0 | K45: =IF(J45,J40/J45,0) -> 0 | L45: =IF(L44,M44/L44,0) -> 0 | M45: =IF(M40,M44/M40*1000,0) -> 0 | N45: =IF(M45,M40/M45,0) -> 0 | O45: =IF(O44,P44/O44,0) -> 0 | P45: =IF(P40,P44/P40*1000,0) -> 0 | Q45: =IF(P45,P40/P45,0) -> 0
B46: 財務レバレッジ補正 | C46: =IF(D44*C44>0,IF((1/(D44/C44+0.33))<1,1,IF((1/(D44/C44+0.33))>1.5,1.5,1/(D44/C44+0.33))),0) -> 0 | F46: =IF(G44*F44>0,IF((1/(G44/F44+0.33))<1,1,IF((1/(G44/F44+0.33))>1.5,1.5,1/(G44/F44+0.33))),0) -> 0 | I46: =IF(J44*I44>0,IF((1/(J44/I44+0.33))<1,1,IF((1/(J44/I44+0.33))>1.5,1.5,1/(J44/I44+0.33))),0) -> 0 | L46: =IF(M44*L44>0,IF((1/(M44/L44+0.33))<1,1,IF((1/(M44/L44+0.33))>1.5,1.5,1/(M44/L44+0.33))),0) -> 0 | O46: =IF(P44*O44>0,IF((1/(P44/O44+0.33))<1,1,IF((1/(P44/O44+0.33))>1.5,1.5,1/(P44/O44+0.33))),0) -> 0
C47: 営業 | D47: 投資 | E47: 財務 | F47: 営業 | G47: 投資 | H47: 財務 | I47: 営業 | J47: 投資 | K47: 財務 | L47: 営業 | M47: 投資 | N47: 財務 | O47: 営業 | P47: 投資 | Q47: 財務
B48: キャッシュフロー
B49: 現金残／FCF | D49: =M22 -> 0 | E49: =C48+D48 -> 0 | H49: =F48+G48 -> 0 | K49: =I48+J48 -> 0 | N49: =L48+M48 -> 0 | Q49: =O48+P48 -> 0
C51: 資産価値 | D51: 事業価値 | E51: 理論株価 | F51: 資産価値 | G51: 事業価値 | H51: 理論株価 | I51: 資産価値 | J51: 事業価値 | K51: 理論株価 | L51: 資産価値 | M51: 事業価値 | N51: 理論株価 | O51: 資産価値 | P51: 事業価値 | Q51: 理論株価
B52: 理論株価 | C52: =D45*IF(C45>=0.8,0.8,IF(C45>=0.67,0.75,IF(C45>=0.5,0.7,IF(C45>=0.33,0.65,IF(C45>=0.1,0.6,0.5))))) -> 0 | D52: =IF(C46>0,IF(D31>0,IF(D41*C44,D41*(D31*0.7/C44*150),0),0)*C46,0) -> 0 | E52: =C52+D52 -> 0 | F52: =G45*IF(F45>=0.8,0.8,IF(F45>=0.67,0.75,IF(F45>=0.5,0.7,IF(F45>=0.33,0.65,IF(F45>=0.1,0.6,0.5))))) -> 0 | G52: =IF(F46>0,IF(G31>0,IF(G41*F44,G41*(G31*0.7/F44*150),0),0)*F46,0) -> 0 | H52: =F52+G52 -> 0 | I52: =J45*IF(I45>=0.8,0.8,IF(I45>=0.67,0.75,IF(I45>=0.5,0.7,IF(I45>=0.33,0.65,IF(I45>=0.1,0.6,0.5))))) -> 0 | J52: =IF(I46>0,IF(J31>0,IF(J41*I44,J41*(J31*0.7/I44*150),0),0)*I46,0) -> 0 | K52: =I52+J52 -> 0 | L52: =M45*IF(L45>=0.8,0.8,IF(L45>=0.67,0.75,IF(L45>=0.5,0.7,IF(L45>=0.33,0.65,IF(L45>=0.1,0.6,0.5))))) -> 0 | M52: =IF(L46>0,IF(M31>0,IF(M41*L44,M41*(M31*0.7/L44*150),0),0)*L46,0) -> 0 | N52: =L52+M52 -> 0 | O52: =P45*IF(O45>=0.8,0.8,IF(O45>=0.67,0.75,IF(O45>=0.5,0.7,IF(O45>=0.33,0.65,IF(O45>=0.1,0.6,0.5))))) -> 0 | P52: =IF(O46>0,IF(P31>0,IF(P41*O44,P41*(P31*0.7/O44*150),0),0)*O46,0) -> 0 | Q52: =O52+P52 -> 0
B53: 株価／理論比 | C53: =L26 -> #VALUE! | D53: =M26 -> 0 | E53: =IF(E52,D53/E52,0) -> 0 | F53: =DATE(LEFT(O4,4),LEFT(P4,LEN(P4)-2)-8,0) -> #VALUE! | H53: =IF(H52,G53/H52,0) -> 0 | I53: =DATE(LEFT(O4,4),LEFT(P4,LEN(P4)-2)-5,0) -> #VALUE! | K53: =IF(K52,J53/K52,0) -> 0 | L53: =DATE(LEFT(O4,4),LEFT(P4,LEN(P4)-2)-2,0) -> #VALUE! | N53: =IF(N52,M53/N52,0) -> 0 | O53: =DATE(LEFT(O4,4),LEFT(P4,LEN(P4)-2)+1,0) -> #VALUE! | Q53: =IF(Q52,P53/Q52,0) -> 0
B54: 上限理論株価 | C54: =C52+(D52*2) -> 0 | F54: =F52+(G52*2) -> 0 | I54: =I52+(J52*2) -> 0 | L54: =L52+(M52*2) -> 0 | O54: =O52+(P52*2) -> 0
C56: 短期借 | D56: 長期借 | E56: 社債 | F56: 短期借 | G56: 長期借 | H56: 社債 | I56: 短期借 | J56: 長期借 | K56: 社債 | L56: 短期借 | M56: 長期借 | N56: 社債 | O56: 短期借 | P56: 長期借 | Q56: 社債
B57: 純有利子負債
B58: 借金返済年数 | E58: =((C57+D57+E57)-D22)/E22 -> #DIV/0! | H58: =((F57+G57+H57)-G22)/H22 -> #DIV/0! | K58: =((I57+J57+K57)-J22)/K22 -> #DIV/0! | N58: =((L57+M57+N57)-M22)/N22 -> #DIV/0! | Q58: =((O57+P57+Q57)-P22)/Q22 -> #DIV/0!
B60: 配当金 | E60: =D60/E22 -> #DIV/0! | H60: =G60/H22 -> #DIV/0! | K60: =J60/K22 -> #DIV/0! | N60: =M60/N22 -> #DIV/0! | Q60: =P60/Q22 -> #DIV/0!
B61: 自己株式取得 | E61: =D61/E22 -> #DIV/0! | H61: =G61/H22 -> #DIV/0! | K61: =J61/K22 -> #DIV/0! | N61: =M61/N22 -> #DIV/0! | Q61: =P61/Q22 -> #DIV/0!
B63: 給与
B64: 賞与
B65: 賞与引当
B66: 退職給付費用
B67: 減価償却費
B69: 目安 | E69: 借金返済目安
B70: 30〜50% → 健全 | E70: 年数 | F70: 評価
B71: 60〜70% → やや高め | E71: 0〜2年 | F71: 超健全
B72: 80%以上 → 危険信号 | E72: 3〜4年 | F72: 普通
B73: 100%以上 → 稼いだ以上に配っている | E73: 5年以上 | F73: やや重い
E74: 7年以上 | F74: 危険水域

Sheet Sheet2
A2: 以下のようなXBRLファイル内タグを使ってエクセルに書き込みたいです。 | K2: XBRLファイル内タグの「contextRef」については以下の種類を使います。
A3: ※ほかにも違う種類のタグがあれば対応できるようにしたい | K3: なお、以下のものは私が把握している限りのものです。ほかにも違う種類があれば対応できるようにしたい。
A4: ※会計基準のIFRSも含む | K4: CurrentYearDuration_NonConsolidatedMember
A5: エクセル表記 | B5: タグ | K5: CurrentYearDuration
A6: 銘柄名 | B6: jpcrp_cor:CompanyNameCoverPage | K6: CurrentYearInstant_NonConsolidatedMember
A7: 決算年 | B7: jpdei_cor:CurrentFiscalYearEndDateDEI | K7: CurrentYearInstant
A8: 決算月 | B8: CurrentFiscalYearEndDateDEIyear | K8: CurrentYTDDuration_NonConsolidatedMember
A9: 売上高 | B9: jppfs_cor:NetSales、jpigp_cor:RevenueIFRS、jpigp_cor:NetSalesIFRS、jpcrp030000-asr_E02144-000:TotalNetRevenuesIFRS | K9: CurrentYTDDuration
A10: 売上原価 | B10: jppfs_cor:CostOfSales、jpigp_cor:CostOfSalesIFRS | K10: CurrentQuarterInstant_NonConsolidatedMember
A11: 売上総利益 | B11: jppfs_cor:GrossProfit、jpigp_cor:GrossProfitIFRS | K11: CurrentQuarterInstant
A12: 販管費 | B12: jppfs_cor:SellingGeneralAndAdministrativeExpenses、jpigp_cor:SellingGeneralAndAdministrativeExpensesIFRS | K12: InterimDuration_NonConsolidatedMember
A13: 営業利益 | B13: jppfs_cor:OperatingIncome、jpigp_cor:OperatingProfitLossIFRS | K13: InterimDuration
A14: 経常利益 | B14: jppfs_cor:OrdinaryIncome、jpigp_cor:ProfitLossBeforeTaxIFRS
A15: 純利益 | B15: jppfs_cor:ProfitLoss、jpigp_cor:ProfitLossIFRS
A16: 発行株数 | B16: jpcrp_cor:TotalNumberOfIssuedSharesSummaryOfBusinessResults、jpcrp_cor:NumberOfIssuedSharesAsOfFiscalYearEndIssuedSharesTotalNumberOfSharesEtc
A17: 資産 | B17: jpcrp_cor:TotalAssetsSummaryOfBusinessResults、jpcrp_cor:TotalAssetsIFRSSummaryOfBusinessResults、jpigp_cor:AssetsIFRS
A18: 資本 | B18: jpcrp_cor:NetAssetsSummaryOfBusinessResults、jpcrp_cor:EquityAttributableToOwnersOfParentIFRSSummaryOfBusinessResults、jpigp_cor:EquityAttributableToOwnersOfParentIFRS
A19: 営業cf | B19: jppfs_cor:NetCashProvidedByUsedInOperatingActivities、jpigp_cor:NetCashProvidedByUsedInOperatingActivitiesIFRS
A20: 投資cf | B20: jppfs_cor:NetCashProvidedByUsedInInvestmentActivities、jpigp_cor:NetCashProvidedByUsedInInvestingActivitiesIFRS
A21: 財務cf | B21: jppfs_cor:NetCashProvidedByUsedInFinancingActivities、jpigp_cor:NetCashProvidedByUsedInFinancingActivitiesIFRS
A22: 現金残／FCF | B22: jppfs_cor:CashAndCashEquivalents、jpigp_cor:CashAndCashEquivalentsIFRS
A23: 短期借 | B23: jppfs_cor:NetIncreaseDecreaseInShortTermLoansPayableFinCF
A24: 長期借 | B24: jppfs_cor:ProceedsFromLongTermLoansPayableFinCF
A25: 社債 | B25: jppfs_cor:ProceedsFromIssuanceOfBondsFinCF
... A33: コード | B33: jpdei_cor:SecurityCodeDEI
